f1z1_async_emitter/__init__.py
f1z1_async_emitter/example.py
f1z1_async_emitter/src/__init__.py
f1z1_async_emitter/src/components/__init__.py
f1z1_async_emitter/src/components/counter/__init__.py
f1z1_async_emitter/src/components/counter/base.py
f1z1_async_emitter/src/components/counter/counter.py
f1z1_async_emitter/src/components/gather/__init__.py
f1z1_async_emitter/src/components/gather/base.py
f1z1_async_emitter/src/components/gather/buffer.py
f1z1_async_emitter/src/components/gather/gather.py
f1z1_async_emitter/src/components/record/__init__.py
f1z1_async_emitter/src/components/record/base.py
f1z1_async_emitter/src/components/record/recorder.py
f1z1_async_emitter/src/components/speed/__init__.py
f1z1_async_emitter/src/components/speed/base.py
f1z1_async_emitter/src/components/speed/speed.py
f1z1_async_emitter/src/components/timeout/__init__.py
f1z1_async_emitter/src/components/timeout/base.py
f1z1_async_emitter/src/components/timeout/timeout.py
f1z1_async_emitter/src/customer/__init__.py
f1z1_async_emitter/src/customer/base.py
f1z1_async_emitter/src/customer/worker_join.py
f1z1_async_emitter/src/producer/__init__.py
f1z1_async_emitter/src/producer/api.py
f1z1_async_emitter/src/producer/base.py
f1z1_async_emitter/src/producer/builder.py
f1z1_async_emitter/src/producer/decorate.py
f1z1_async_emitter/src/producer/factory.py
f1z1_async_emitter/src/producer/handler.py
f1z1_async_emitter/src/producer/master.py
f1z1_async_emitter/src/producer/worker.py
f1z1_async_emitter-0.2.7.dist-info/LICENSE
f1z1_async_emitter-0.2.7.dist-info/METADATA
f1z1_async_emitter-0.2.7.dist-info/WHEEL
f1z1_async_emitter-0.2.7.dist-info/top_level.txt
f1z1_async_emitter-0.2.7.dist-info/RECORD
